Metadata-Version: 2.1
Name: clas___files123456
Version: 0.1
Summary: Удобный класс для работы с файлами
Author-email: nikVCS@yandex.by
